<?xml version="1.0" encoding="utf-8"?>
<clothing-items>
 <clothing>
  <id>
   976756456
  </id>
  <name>
   Fila Hat G-7611
  </name>
  <category>
   Hat
  </category>
  <size>
   XXL
  </size>
  <color>
   Фиолетовый
  </color>
  <material>
   Кожа
  </material>
  <price>
   172711
  </price>
  <rating>
   4.18
  </rating>
  <reviews>
   680637
  </reviews>
  <new>
   -
  </new>
  <exclusive>
   no
  </exclusive>
 </clothing>
 <clothing>
  <id>
   874260461
  </id>
  <name>
   Fila Gloves E-7694
  </name>
  <category>
   Gloves
  </category>
  <size>
   S
  </size>
  <color>
   Зеленый
  </color>
  <material>
   Шелк
  </material>
  <price>
   912927
  </price>
  <rating>
   3.5
  </rating>
  <reviews>
   304656
  </reviews>
  <exclusive>
   yes
  </exclusive>
 </clothing>
 <clothing>
  <id>
   652682185
  </id>
  <name>
   Lacoste Belts I-6160
  </name>
  <category>
   Belts
  </category>
  <size>
   S
  </size>
  <color>
   Оранжевый
  </color>
  <material>
   Лен
  </material>
  <price>
   106546
  </price>
  <rating>
   3.51
  </rating>
  <reviews>
   655028
  </reviews>
  <new>
   -
  </new>
  <exclusive>
   no
  </exclusive>
  <sporty>
   yes
  </sporty>
 </clothing>
 <clothing>
  <id>
   292944861
  </id>
  <name>
   Addidas Umbrellas P-7845
  </name>
  <category>
   Umbrellas
  </category>
  <size>
   XXL
  </size>
  <color>
   Красный
  </color>
  <material>
   Шерсть
  </material>
  <price>
   563770
  </price>
  <rating>
   4.0
  </rating>
  <reviews>
   279991
  </reviews>
  <new>
   +
  </new>
  <sporty>
   no
  </sporty>
 </clothing>
 <clothing>
  <id>
   810206485
  </id>
  <name>
   Lacoste Sweater Z-9781
  </name>
  <category>
   Sweater
  </category>
  <size>
   XXL
  </size>
  <color>
   Зеленый
  </color>
  <material>
   Шелк
  </material>
  <price>
   360162
  </price>
  <rating>
   2.78
  </rating>
  <reviews>
   213575
  </reviews>
  <exclusive>
   no
  </exclusive>
  <sporty>
   yes
  </sporty>
 </clothing>
 <clothing>
  <id>
   839773908
  </id>
  <name>
   PleinSport Jeans V-2185
  </name>
  <category>
   Jeans
  </category>
  <size>
   XL
  </size>
  <color>
   Синий
  </color>
  <material>
   Кожа
  </material>
  <price>
   749766
  </price>
  <rating>
   4.85
  </rating>
  <reviews>
   50170
  </reviews>
  <new>
   +
  </new>
  <exclusive>
   no
  </exclusive>
  <sporty>
   yes
  </sporty>
 </clothing>
 <clothing>
  <id>
   501216167
  </id>
  <name>
   Nike Gloves Y-4350
  </name>
  <category>
   Gloves
  </category>
  <size>
   XL
  </size>
  <color>
   Красный
  </color>
  <material>
   Шерсть
  </material>
  <price>
   392214
  </price>
  <rating>
   4.8
  </rating>
  <reviews>
   655489
  </reviews>
  <new>
   -
  </new>
  <exclusive>
   no
  </exclusive>
 </clothing>
 <clothing>
  <id>
   398168256
  </id>
  <name>
   Nike Dress L-5507
  </name>
  <category>
   Dress
  </category>
  <size>
   XXL
  </size>
  <color>
   Зеленый
  </color>
  <material>
   Лен
  </material>
  <price>
   135708
  </price>
  <rating>
   1.27
  </rating>
  <reviews>
   829084
  </reviews>
  <new>
   -
  </new>
  <exclusive>
   yes
  </exclusive>
 </clothing>
 <clothing>
  <id>
   583347876
  </id>
  <name>
   Ellesse Jacket S-5014
  </name>
  <category>
   Jacket
  </category>
  <size>
   M
  </size>
  <color>
   Зеленый
  </color>
  <material>
   Хлопок
  </material>
  <price>
   139043
  </price>
  <rating>
   2.56
  </rating>
  <reviews>
   712303
  </reviews>
  <new>
   -
  </new>
 </clothing>
 <clothing>
  <id>
   360601133
  </id>
  <name>
   Vans Sweater M-4901
  </name>
  <category>
   Sweater
  </category>
  <size>
   L
  </size>
  <color>
   Красный
  </color>
  <material>
   Хлопок
  </material>
  <price>
   315597
  </price>
  <rating>
   1.87
  </rating>
  <reviews>
   557361
  </reviews>
  <new>
   -
  </new>
 </clothing>
 <clothing>
  <id>
   333663846
  </id>
  <name>
   Ellesse Shirt U-9025
  </name>
  <category>
   Shirt
  </category>
  <size>
   XL
  </size>
  <color>
   Желтый
  </color>
  <material>
   Шелк
  </material>
  <price>
   154235
  </price>
  <rating>
   4.23
  </rating>
  <reviews>
   613544
  </reviews>
  <new>
   +
  </new>
  <sporty>
   no
  </sporty>
 </clothing>
 <clothing>
  <id>
   940728790
  </id>
  <name>
   Adidas T-shirt W-9124
  </name>
  <category>
   T-shirt
  </category>
  <size>
   XXL
  </size>
  <color>
   Желтый
  </color>
  <material>
   Нейлон
  </material>
  <price>
   196958
  </price>
  <rating>
   1.72
  </rating>
  <reviews>
   919233
  </reviews>
  <new>
   -
  </new>
 </clothing>
 <clothing>
  <id>
   740378152
  </id>
  <name>
   Addidas Shirt M-1406
  </name>
  <category>
   Shirt
  </category>
  <size>
   L
  </size>
  <color>
   Оранжевый
  </color>
  <material>
   Полиэстер
  </material>
  <price>
   227220
  </price>
  <rating>
   3.03
  </rating>
  <reviews>
   610727
  </reviews>
  <sporty>
   yes
  </sporty>
 </clothing>
 <clothing>
  <id>
   748274723
  </id>
  <name>
   Fila Gloves H-6597
  </name>
  <category>
   Gloves
  </category>
  <size>
   S
  </size>
  <color>
   Синий
  </color>
  <material>
   Шелк
  </material>
  <price>
   499037
  </price>
  <rating>
   4.03
  </rating>
  <reviews>
   982113
  </reviews>
  <new>
   +
  </new>
  <sporty>
   no
  </sporty>
 </clothing>
 <clothing>
  <id>
   857987934
  </id>
  <name>
   Addidas Skirt X-7434
  </name>
  <category>
   Skirt
  </category>
  <size>
   S
  </size>
  <color>
   Красный
  </color>
  <material>
   Нейлон
  </material>
  <price>
   456065
  </price>
  <rating>
   4.83
  </rating>
  <reviews>
   393333
  </reviews>
  <new>
   +
  </new>
  <sporty>
   yes
  </sporty>
 </clothing>
 <clothing>
  <id>
   266761714
  </id>
  <name>
   New Balance Jacket A-7065
  </name>
  <category>
   Jacket
  </category>
  <size>
   S
  </size>
  <color>
   Фиолетовый
  </color>
  <material>
   Лен
  </material>
  <price>
   228396
  </price>
  <rating>
   4.73
  </rating>
  <reviews>
   23506
  </reviews>
  <sporty>
   no
  </sporty>
 </clothing>
 <clothing>
  <id>
   838991349
  </id>
  <name>
   Puma Jeans Q-1219
  </name>
  <category>
   Jeans
  </category>
  <size>
   L
  </size>
  <color>
   Фиолетовый
  </color>
  <material>
   Вискоза
  </material>
  <price>
   941692
  </price>
  <rating>
   2.01
  </rating>
  <reviews>
   987948
  </reviews>
  <new>
   +
  </new>
  <sporty>
   no
  </sporty>
 </clothing>
</clothing-items>
